{"nodes": [{"id": "magit_authors_md", "label": "Magit Authors", "file_type": "document", "source_file": "zeemacs.d/elpa/magit-20251122.1529/AUTHORS.md", "description": "Magit project authors and contributors list, documenting contributions to the Git interface for Emacs."}], "edges": [{"source": "magit_authors_md", "target": "magit_package", "relation": "references", "confidence": "INFERRED", "confidence_score": 0.95, "source_file": "zeemacs.d/elpa/magit-20251122.1529/AUTHORS.md"}], "hyperedges": []}