{"nodes": [{"id": "users_zakaria_dotfiles_zeemacs_d_elpa_aio_20251117_644_readme_md", "label": "README.md", "file_type": "document", "source_file": "/Users/zakaria/dotfiles/zeemacs.d/elpa/aio-20251117.644/README.md", "source_location": "L1"}, {"id": "aio_20251117_644_readme_aio_async_await_for_emacs_lisp", "label": "aio: async/await for Emacs Lisp", "file_type": "document", "source_file": "/Users/zakaria/dotfiles/zeemacs.d/elpa/aio-20251117.644/README.md", "source_location": "L1"}, {"id": "aio_20251117_644_readme_usage", "label": "Usage", "file_type": "document", "source_file": "/Users/zakaria/dotfiles/zeemacs.d/elpa/aio-20251117.644/README.md", "source_location": "L13"}, {"id": "aio_20251117_644_readme_utility_macros_and_functions", "label": "Utility macros and functions", "file_type": "document", "source_file": "/Users/zakaria/dotfiles/zeemacs.d/elpa/aio-20251117.644/README.md", "source_location": "L61"}, {"id": "aio_20251117_644_readme_awaitable_functions", "label": "Awaitable functions", "file_type": "document", "source_file": "/Users/zakaria/dotfiles/zeemacs.d/elpa/aio-20251117.644/README.md", "source_location": "L87"}, {"id": "aio_20251117_644_readme_select_api", "label": "Select API", "file_type": "document", "source_file": "/Users/zakaria/dotfiles/zeemacs.d/elpa/aio-20251117.644/README.md", "source_location": "L106"}, {"id": "aio_20251117_644_readme_semaphore_api", "label": "Semaphore API", "file_type": "document", "source_file": "/Users/zakaria/dotfiles/zeemacs.d/elpa/aio-20251117.644/README.md", "source_location": "L141"}], "edges": [{"source": "users_zakaria_dotfiles_zeemacs_d_elpa_aio_20251117_644_readme_md", "target": "aio_20251117_644_readme_aio_async_await_for_emacs_lisp", "relation": "contains", "confidence": "EXTRACTED", "source_file": "/Users/zakaria/dotfiles/zeemacs.d/elpa/aio-20251117.644/README.md", "source_location": "L1", "weight": 1.0}, {"source": "aio_20251117_644_readme_aio_async_await_for_emacs_lisp", "target": "aio_20251117_644_readme_usage", "relation": "contains", "confidence": "EXTRACTED", "source_file": "/Users/zakaria/dotfiles/zeemacs.d/elpa/aio-20251117.644/README.md", "source_location": "L13", "weight": 1.0}, {"source": "aio_20251117_644_readme_aio_async_await_for_emacs_lisp", "target": "aio_20251117_644_readme_utility_macros_and_functions", "relation": "contains", "confidence": "EXTRACTED", "source_file": "/Users/zakaria/dotfiles/zeemacs.d/elpa/aio-20251117.644/README.md", "source_location": "L61", "weight": 1.0}, {"source": "aio_20251117_644_readme_aio_async_await_for_emacs_lisp", "target": "aio_20251117_644_readme_awaitable_functions", "relation": "contains", "confidence": "EXTRACTED", "source_file": "/Users/zakaria/dotfiles/zeemacs.d/elpa/aio-20251117.644/README.md", "source_location": "L87", "weight": 1.0}, {"source": "aio_20251117_644_readme_aio_async_await_for_emacs_lisp", "target": "aio_20251117_644_readme_select_api", "relation": "contains", "confidence": "EXTRACTED", "source_file": "/Users/zakaria/dotfiles/zeemacs.d/elpa/aio-20251117.644/README.md", "source_location": "L106", "weight": 1.0}, {"source": "aio_20251117_644_readme_aio_async_await_for_emacs_lisp", "target": "aio_20251117_644_readme_semaphore_api", "relation": "contains", "confidence": "EXTRACTED", "source_file": "/Users/zakaria/dotfiles/zeemacs.d/elpa/aio-20251117.644/README.md", "source_location": "L141", "weight": 1.0}], "input_tokens": 0, "output_tokens": 0}